brapi_proxy/__init__.py
brapi_proxy/_version.py
brapi_proxy/brapi.py
brapi_proxy/config_demo.ini
brapi_proxy/handler.py
brapi_proxy/service.py
brapi_proxy/core/__init__.py
brapi_proxy/core/core_commoncropnames.py
brapi_proxy/core/core_lists.py
brapi_proxy/core/core_locations.py
brapi_proxy/core/core_people.py
brapi_proxy/core/core_programs.py
brapi_proxy/core/core_seasons.py
brapi_proxy/core/core_serverinfo.py
brapi_proxy/core/core_studies.py
brapi_proxy/core/core_trials.py
brapi_proxy/genotyping/__init__.py
brapi_proxy/genotyping/genotyping_allelematrix.py
brapi_proxy/genotyping/genotyping_callsets.py
brapi_proxy/genotyping/genotyping_plates.py
brapi_proxy/genotyping/genotyping_references.py
brapi_proxy/genotyping/genotyping_referencesets.py
brapi_proxy/genotyping/genotyping_samples.py
brapi_proxy/genotyping/genotyping_variants.py
brapi_proxy/genotyping/genotyping_variantsets.py
brapi_proxy/germplasm/__init__.py
brapi_proxy/germplasm/germplasm_attributes.py
brapi_proxy/germplasm/germplasm_attributevalues.py
brapi_proxy/germplasm/germplasm_breedingmethods.py
brapi_proxy/germplasm/germplasm_germplasm.py
brapi_proxy/phenotyping/__init__.py
brapi_proxy/phenotyping/phenotyping_methods.py
brapi_proxy/phenotyping/phenotyping_observations.py
brapi_proxy/phenotyping/phenotyping_observationunits.py
brapi_proxy/phenotyping/phenotyping_ontologies.py
brapi_proxy/phenotyping/phenotyping_scales.py
brapi_proxy/phenotyping/phenotyping_traits.py
brapi_proxy/phenotyping/phenotyping_variables.py
brapi_proxy-0.9.0.dist-info/LICENSE
brapi_proxy-0.9.0.dist-info/METADATA
brapi_proxy-0.9.0.dist-info/WHEEL
brapi_proxy-0.9.0.dist-info/entry_points.txt
brapi_proxy-0.9.0.dist-info/top_level.txt
brapi_proxy-0.9.0.dist-info/RECORD
