Metadata-Version: 2.1
Name: brapi-proxy
Version: 0.9.0
Summary: A BRAPI server instance that functions as a proxy to merge and combine endpoints from existing BRAPI services
Author-email: Matthijs Brouwer <matthijs.brouwer@wur.nl>
License: MIT License
Project-URL: Homepage, https://github.com/matthijsbrouwer/brapi-proxy
Classifier: Topic :: Internet :: Proxy Servers
Classifier: Topic :: Scientific/Engineering :: Bio-Informatics
Classifier: Programming Language :: Python :: 3.10
Classifier: Operating System :: OS Independent
Requires-Python: >=3.10
License-File: LICENSE
Requires-Dist: Flask==3.1.0
Requires-Dist: flask_restx==1.3.0
Requires-Dist: Requests==2.32.3
Requires-Dist: waitress==3.0.2
